README.rst
gibiexport.py
setup.py
gibiexport.egg-info/PKG-INFO
gibiexport.egg-info/SOURCES.txt
gibiexport.egg-info/dependency_links.txt
gibiexport.egg-info/requires.txt
gibiexport.egg-info/top_level.txt