Metadata-Version: 1.1
Name: gibiexport
Version: 0.1.2
Summary: Tool for exporting github issues into bitbucket issues export format
Home-page: https://bitbucket.org/ZyX_I/gibiexport
Author: Nikolay Pavlov
Author-email: kp-pav@yandex.ru
License: CC-BY-SA-4.0
Download-URL: https://bitbucket.org/ZyX_I/gibiexport/get/default.tar.bz2
Platform: UNKNOWN
